django_lock.py
django_cache_lock-0.2.5.dist-info/LICENSE
django_cache_lock-0.2.5.dist-info/METADATA
django_cache_lock-0.2.5.dist-info/WHEEL
django_cache_lock-0.2.5.dist-info/top_level.txt
django_cache_lock-0.2.5.dist-info/RECORD
